async_rmq/_init_.py
async_rmq/abstract_rmq_consumer.py
async_rmq/abstract_rmq_rpc_server.py
async_rmq/abtract_rmq_rpc_client.py
async_rmq/consumer_threading.py
async_rmq/rmq_functions.py
async_rmq-0.3.1.dist-info/LICENSE
async_rmq-0.3.1.dist-info/METADATA
async_rmq-0.3.1.dist-info/WHEEL
async_rmq-0.3.1.dist-info/top_level.txt
async_rmq-0.3.1.dist-info/RECORD
