Metadata-Version: 2.1
Name: async-rmq
Version: 0.3.1
Summary: Module for working with asynchronous RabbitMQ library
Author-email: Konstantin Zakharov <konstantizaharov@gmail.com>
Project-URL: Homepage, https://pypi.org/project/async-rmq/
Classifier: Programming Language :: Python :: 3
Classifier: License :: OSI Approved :: MIT License
Classifier: Operating System :: OS Independent
Requires-Python: >=3.8
License-File: LICENSE
